protocols_io_mcp/__init__.py
protocols_io_mcp/__main__.py
protocols_io_mcp/server.py
protocols_io_mcp/tools/__init__.py
protocols_io_mcp/tools/protocol.py
protocols_io_mcp/utils/__init__.py
protocols_io_mcp/utils/config.py
protocols_io_mcp/utils/helpers.py
protocols_io_mcp-1.0.3.dist-info/METADATA
protocols_io_mcp-1.0.3.dist-info/WHEEL
protocols_io_mcp-1.0.3.dist-info/entry_points.txt
protocols_io_mcp-1.0.3.dist-info/licenses/LICENSE
protocols_io_mcp-1.0.3.dist-info/RECORD
