Metadata-Version: 2.4
Name: protocols-io-mcp
Version: 1.0.3
Summary: An MCP server that enables MCP clients like Claude Desktop to interact with data from protocols.io.
Project-URL: Homepage, https://github.com/hqn21/protocols-io-mcp-server
Project-URL: Issues, https://github.com/hqn21/protocols-io-mcp-server/issues
Author-email: Hao-Quan Liu <contact@haoquan.me>
License-Expression: MIT
License-File: LICENSE
Classifier: Development Status :: 5 - Production/Stable
Classifier: Intended Audience :: Developers
Classifier: Intended Audience :: Science/Research
Classifier: License :: OSI Approved :: MIT License
Classifier: Operating System :: OS Independent
Classifier: Programming Language :: Python :: 3
Classifier: Programming Language :: Python :: 3.10
Classifier: Programming Language :: Python :: 3.11
Classifier: Programming Language :: Python :: 3.12
Classifier: Programming Language :: Python :: 3.13
Requires-Python: >=3.10
Requires-Dist: click>=8.2.1
Requires-Dist: fastmcp>=2.14.3
Requires-Dist: httpx>=0.28.1
Provides-Extra: dev
Requires-Dist: build>=1.3.0; extra == 'dev'
Requires-Dist: pytest-asyncio>=1.1.0; extra == 'dev'
Requires-Dist: pytest-mock>=3.14.1; extra == 'dev'
Requires-Dist: pytest>=8.4.1; extra == 'dev'
Requires-Dist: python-dotenv>=1.1.1; extra == 'dev'
Requires-Dist: twine>=6.1.0; extra == 'dev'
